calculator/__init__.py
calculator/calculator.py
tests/__init__.py
tests/test_calculator.py
turing_calculator_package-0.2.dist-info/LICENSE.txt
turing_calculator_package-0.2.dist-info/METADATA
turing_calculator_package-0.2.dist-info/WHEEL
turing_calculator_package-0.2.dist-info/top_level.txt
turing_calculator_package-0.2.dist-info/RECORD
